Workbook
Name Slicer_Category: #N/A
Name Slicer_Region: #N/A

Sheet Raw_Sales_Data
A1: Order_ID | B1: Order_Date | C1: Region | D1: State | E1: Salesperson | F1: Category | G1: Product | H1: Quantity | I1: Unit_Price | J1: Discount | K1: Revenue | L1: Cost | M1: Profit | N1: Customer_Type | O1: Payment_Mode
A2: ORD10001 | B2: 45745 | C2: South | D2: Telangana | E2: Arjun | F2: Office Supplies | G2: Stationery Kit | H2: 5 | I2: 661.47 | J2: 0.03 | K2: 3208.15 | L2: 2033.77 | M2: 1174.38 | N2: Retail | O2: Debit Card
A3: ORD10002 | B3: 45910 | C3: NORTH | D3: Punjab | E3: Kavya | F3: Furniture | G3: Dining Table | H3: 8 | I3: 30205.11 | J3: 0.08 | K3: 222309.59 | L3: 170466.27 | M3: 51843.32 | N3: Corporate | O3: UPI
A4: ORD10003 | B4: 46021 | C4: South | D4: Tamil Nadu | E4: Priya | F4: Electronics | G4: Monitor | H4: 8 | I4: 17230.38 | J4: 0 | K4: 137843.05 | L4: 105920.34 | M4: 31922.71 | N4: Corporate | O4: UPI
A5: ORD10004 | B5: 46003 | C5: North | D5: Haryana | E5: Arjun | F5: Electronics | G5: Smartphone | H5: 4 | I5: 32122.57 | J5: 0.05 | K5: 122065.76 | L5: 86971.85 | M5: 35093.91 | N5: Retail | O5: Net Banking
A6: ORD10005 | B6: 45711 | C6: North | D6: Uttar Pradesh | E6: Arjun | F6: Home Appliances | G6: Microwave | H6: 6 | I6: 11790.84 | J6: 0.03 | K6: 68622.67 | L6: 54986.44 | M6: 13636.23 | N6: Corporate | O6: Cash
A7: ORD10006 | B7: 45909 | C7: WEST | D7: Gujarat | E7: Sneha | F7: Furniture | G7: Bed | H7: 6 | I7: 31090.91 | K7: 180949.07 | L7: 136961.54 | M7: 43987.53 | N7: Retail | O7: Cash
A8: ORD10007 | B8: 45672 | C8: South | D8: Karnataka | E8: Arjun | F8: Furniture | G8: Dining Table | H8: 1 | I8: 27018.59 | J8: 0.05 | K8: 25667.66 | L8: 16782.08 | M8: 8885.58 | N8: Retail | O8: UPI
A9: ORD10008 | B9: 45918 | C9: West | D9: Goa | E9: Amit | F9: Electronics | G9: Tablet | H9: 3 | I9: 22728.14 | J9: 0.08 | K9: 62729.66 | L9: 50503.96 | M9: 12225.7 | N9: Online | O9: Credit Card
A10: ORD10009 | B10: 45756 | C10: North | D10: Haryana | E10: Amit | F10: Office Supplies | G10: Office Chair | H10: 1 | I10: 8371.52 | J10: 0.03 | K10: 8120.38 | L10: 5668.38 | M10: 2452 | N10: Corporate | O10: Debit Card
A11: ORD10010 | B11: 45940 | C11: East | D11: Bihar | E11: Vikram | F11: Furniture | G11: Bookshelf | H11: 1 | I11: 11390.24 | J11: 0.03 | K11: 11048.54 | L11: 7529.1 | M11: 3519.44 | N11: Corporate | O11: Credit Card
A12: ORD10011 | B12: 45888 | C12: North | D12: Delhi | E12: Rahul | F12: Electronics | G12: Laptop | H12: 4 | I12: 65658.07 | J12: 0.08 | K12: 241621.68 | L12: 157885.16 | M12: 83736.52 | N12: Retail | O12: Debit Card
A13: ORD10012 | B13: 45791 | C13: North | D13: Delhi | E13: Kavya | F13: Home Appliances | G13: Microwave | H13: 6 | I13: 12730.5 | J13: 0.08 | K13: 70272.35 | L13: 48554.83 | M13: 21717.52 | N13: Corporate | O13: Net Banking
A14: ORD10013 | B14: 45940 | C14: North | D14: Punjab | E14: Neha | F14: Home Appliances | G14: Washing Machine | H14: 7 | I14: 38281.49 | J14: 0.03 | K14: 259931.29 | L14: 168022.83 | M14: 91908.46 | N14: Corporate | O14: Net Banking
A15: ORD10014 | B15: 45809 | C15: South | D15: Tamil Nadu | E15: Arjun | F15: Electronics | G15: Tablet | H15: 1 | I15: 21946.6 | J15: 0.08 | K15: 20190.87 | L15: 13823.86 | M15: 6367.01 | N15: Online | O15: UPI
A16: ORD10015 | B16: 45738 | C16: South | D16: Karnataka | E16: Amit | F16: Electronics | G16: Monitor | H16: 6 | I16: 18565.36 | J16: 0.08 | K16: 102480.77 | L16: 67180.33 | M16: 35300.44 | N16: Retail | O16: Credit Card
A17: ORD10016 | B17: 45817 | C17: South | D17: Karnataka | E17: Arjun | F17: Electronics | G17: Laptop | H17: 1 | I17: 62291.44 | J17: 0 | K17: 62291.44 | L17: 45937.98 | M17: 16353.46 | N17: Corporate | O17: Net Banking
A18: ORD10017 | B18: 45801 | C18: North | D18: Uttar Pradesh | E18: Rahul | F18: Electronics | G18: Headphones | H18: 4 | I18: 4848.06 | J18: 0.05 | K18: 18422.65 | L18: 15031.84 | M18: 3390.81 | N18: Online | O18: Net Banking
A19: ORD10018 | B19: 45805 | C19: South | D19: Andhra Pradesh | E19: Vikram | F19: Furniture | G19: Bed | H19: 3 | I19: 28657.16 | J19: 0.08 | K19: 79093.75 | L19: 64404.48 | M19: 14689.27 | N19: Corporate | O19: Net Banking
... A39: ORD10038 | B39: 45669 | C39: South | D39: Tamil Nadu | E39: Rahul | F39: Furniture | G39: Bookshelf | H39: 1 | I39: 11811.7 | J39: 0.1 | K39: 10630.53 | L39: 7090.46 | M39: 3540.07 | N39: Retail | O39: Credit Card
A40: ORD10039 | C40: North | D40: Punjab | E40: Rahul | F40: Electronics | G40: Smartphone | H40: 8 | I40: 29449.9 | J40: 0.08 | K40: 216751.29 | L40: 152105.2 | M40: 64646.09 | N40: Retail | O40: Net Banking
A41: ORD10040 | B41: 45849 | C41: East | D41: Odisha | E41: Vikram | F41: Furniture | G41: Bed | H41: 1 | I41: 31456.71 | J41: 0.03 | K41: 30513.01 | L41: 20217.48 | M41: 10295.53 | N41: Corporate | O41: Debit Card
A42: ORD10041 | B42: 46018 | C42: South | D42: Karnataka | E42: Amit | F42: Office Supplies | G42: Stationery Kit | H42: 4 | I42: 692.05 | J42: 0.08 | K42: 2546.73 | L42: 2040.16 | M42: 506.57 | N42: Retail | O42: UPI
A43: ORD10042 | B43: 45733 | C43: South | D43: Andhra Pradesh | E43: Amit | F43: Electronics | G43: Tablet | H43: 3 | I43: 21609.99 | J43: 0 | K43: 64829.97 | L43: 54281.59 | M43: 10548.38 | N43: Retail | O43: Net Banking
A44: ORD10043 | B44: 45710 | C44: West | D44: Goa | E44: Sneha | F44: Home Appliances | G44: Mixer Grinder | H44: 5 | I44: 4834.57 | J44: 0.03 | K44: 23447.66 | L44: 18322.11 | M44: 5125.55 | N44: Online | O44: UPI
A45: ORD10044 | B45: 45896 | C45: North | D45: Delhi | E45: Priya | F45: Furniture | G45: Dining Table | H45: 5 | I45: 29061.92 | J45: 0.05 | K45: 138044.12 | L45: 108971.97 | M45: 29072.15 | N45: Retail | O45: Credit Card
A46: ORD10045 | B46: 45662 | C46: West | D46: Maharashtra | E46: Vikram | F46: Furniture | G46: Coffee Table | H46: 8 | I46: 7918.96 | J46: 0.1 | K46: 57016.5 | L46: 45014.42 | M46: 12002.08 | N46: Corporate | O46: Debit Card
A47: ORD10046 | B47: 45909 | C47: East | D47: West Bengal | E47: Amit | F47: Furniture | G47: Sofa | H47: 7 | I47: 34087.39 | J47: 0.08 | K47: 219522.8 | L47: 154555.55 | M47: 64967.25 | N47: Retail | O47: Cash
A48: ORD10047 | B48: 45783 | C48: South | D48: Tamil Nadu | E48: Rahul | F48: Electronics | G48: Tablet | H48: 7 | I48: 21769.27 | J48: 0.03 | K48: 147813.35 | L48: 106018.9 | M48: 41794.45 | N48: Retail | O48: Net Banking
A49: ORD10048 | B49: 45969 | C49: East | D49: Bihar | E49: Amit | F49: Office Supplies | G49: Desk | H49: 5 | I49: 13412.01 | J49: 0.05 | K49: 63707.07 | L49: 46802.5 | M49: 16904.57 | N49: Corporate | O49: Cash
A50: ORD10049 | B50: 45886 | C50: West | D50: Goa | E50: Vikram | F50: Furniture | G50: Coffee Table | H50: 7 | I50: 9031.95 | J50: 0.05 | K50: 60062.5 | L50: 51552.34 | M50: 8510.16 | N50: Retail | O50: Debit Card
A51: ORD10050 | B51: 45669 | C51: West | D51: Gujarat | E51: Arjun | F51: Office Supplies | G51: Printer | H51: 5 | I51: 15472.62 | J51: 0.05 | K51: 73494.95 | L51: 58568.43 | M51: 14926.52 | N51: Online | O51: Net Banking
A52: ORD10051 | B52: 46014 | C52: North | D52: Delhi | E52: Kavya | F52: Electronics | G52: Monitor | H52: 2 | I52: 17678.21 | J52: 0.03 | K52: 34295.73 | L52: 23452.28 | M52: 10843.45 | N52: Online | O52: Debit Card
A53: ORD10052 | B53: 45910 | C53: East | D53: West Bengal | E53: Amit | F53: Electronics | G53: Monitor | H53: 5 | I53: 18532.03 | J53: 0.03 | K53: 89880.33 | L53: 75375.67 | M53: 14504.66 | N53: Online | O53: Debit Card
A54: ORD10053 | B54: 45722 | C54: East | D54: Bihar | E54: Amit | F54: Home Appliances | G54: Washing Machine | H54: 3 | I54: 33380.46 | J54: 0 | K54: 100141.38 | L54: 71135.55 | M54: 29005.83 | N54: Corporate | O54: UPI
A55: ORD10054 | B55: 45968 | C55: South | D55: Karnataka | E55: Arjun | F55: Home Appliances | G55: Microwave | H55: 3 | I55: 12132.64 | J55: 0 | K55: 36397.91 | L55: 22888.36 | M55: 13509.55 | N55: Online | O55: UPI
A56: ORD10055 | C56: South | D56: Telangana | E56: Neha | F56: Furniture | G56: Coffee Table | H56: 5 | I56: 9104.88 | J56: 0.1 | K56: 40971.97 | L56: 27834.86 | M56: 13137.11 | N56: Retail | O56: UPI
A57: ORD10056 | B57: 45811 | C57: West | D57: Maharashtra | E57: Sneha | F57: Electronics | G57: Laptop | H57: 8 | I57: 66228.53 | J57: 0.05 | K57: 503336.86 | L57: 325786.71 | M57: 177550.15 | N57: Corporate | O57: Debit Card
A58: ORD10057 | B58: 45960 | C58: South | D58: Andhra Pradesh | E58: Amit | F58: Home Appliances | G58: Mixer Grinder | H58: 6 | I58: 5301.32 | J58: 0.05 | K58: 30217.54 | L58: 19706.78 | M58: 10510.76 | N58: Corporate | O58: Cash
A59: ORD10058 | B59: 46004 | C59: East | D59: Odisha | E59: Rahul | F59: Electronics | G59: Monitor | H59: 2 | I59: 17569.69 | J59: 0.08 | K59: 32328.23 | L59: 23086.84 | M59: 9241.39 | N59: Retail | O59: Credit Card
A60: ORD10059 | B60: 45795 | C60: South | D60: Karnataka | E60: Amit | F60: Office Supplies | G60: Notebook | H60: 6 | I60: 254.88 | J60: 0.1 | K60: 1376.37 | L60: 1167 | M60: 209.37 | N60: Online | O60: Credit Card
A61: ORD10060 | B61: 45768 | C61: East | D61: Jharkhand | E61: Kavya | F61: Electronics | G61: Headphones | H61: 2 | I61: 4376.7 | J61: 0.08 | K61: 8053.13 | L61: 5457.08 | M61: 2596.05 | N61: Retail | O61: Debit Card
A62: ORD10061 | B62: 45718 | C62: North | D62: Uttar Pradesh | E62: Sneha | F62: Electronics | G62: Laptop | H62: 3 | I62: 68892.9 | J62: 0.05 | K62: 196344.77 | L62: 167589.39 | M62: 28755.38 | N62: Retail | O62: Debit Card
A63: ORD10062 | B63: 45691 | C63: West | D63: Gujarat | E63: Sneha | F63: Electronics | G63: Headphones | H63: 6 | I63: 4226.86 | J63: 0.05 | K63: 24093.09 | L63: 16130.81 | M63: 7962.28 | N63: Retail | O63: Credit Card
A64: ORD10063 | B64: 45718 | C64: East | D64: West Bengal | E64: Priya | F64: Office Supplies | G64: Printer | H64: 6 | I64: 13996.22 | J64: 0.1 | K64: 75579.6 | L64: 63563.15 | M64: 12016.45 | N64: Retail | O64: Net Banking
A65: ORD10064 | B65: 45671 | C65: West | D65: Maharashtra | E65: Rahul | F65: electronics | G65: Smartphone | H65: 4 | I65: 29370.79 | J65: 0.05 | K65: 111608.98 | L65: 89219.44 | M65: 22389.54 | N65: Retail | O65: Debit Card
A66: ORD10065 | B66: 45849 | C66: East | D66: Bihar | E66: Arjun | F66: Home Appliances | G66: Air Conditioner | H66: 5 | I66: 50820.21 | J66: 0.05 | K66: 241396 | L66: 172675.22 | M66: 68720.78 | N66: Retail | O66: Cash
A67: ORD10066 | B67: 45725 | C67: North | D67: Haryana | E67: Amit | F67: Furniture | G67: Dining Table | H67: 6 | I67: 26296.53 | J67: 0.1 | K67: 142001.29 | L67: 108270.61 | M67: 33730.68 | N67: Retail | O67: UPI
A68: ORD10067 | B68: 45758 | C68: South | D68: Tamil Nadu | E68: Sneha | F68: Home Appliances | G68: Washing Machine | H68: 7 | I68: 37413.73 | J68: 0.05 | K68: 248801.31 | L68: 161874.93 | M68: 86926.38 | N68: Retail | O68: Credit Card
... A70: ORD10069 | B70: 45880 | C70: North | D70: Punjab | E70: Arjun | F70: Electronics | G70: Laptop | H70: 7 | I70: 60337.01 | J70: 0 | K70: 422359.06 | L70: 332510.93 | M70: 89848.13 | N70: Online | O70: Net Banking
A71: ORD10070 | B71: 45992 | C71: West | D71: Goa | E71: Arjun | F71: Office Supplies | G71: Printer | H71: 6 | I71: 14210.13 | J71: 0.08 | K71: 78439.92 | L71: 66128.79 | M71: 12311.13 | N71: Corporate | O71: Credit Card
A72: ORD10071 | B72: 45658 | C72: North | D72: Uttar Pradesh | E72: Vikram | F72: Electronics | G72: Monitor | H72: 3 | I72: 17134.58 | J72: 0.08 | K72: 47291.44 | L72: 35334.35 | M72: 11957.09 | N72: Corporate | O72: Cash
A73: ORD10072 | B73: 45795 | C73: South | D73: Tamil Nadu | E73: Sneha | F73: Electronics | G73: Tablet | H73: 1 | I73: 21539.69 | J73: 0.05 | K73: 20462.71 | L73: 15381.1 | M73: 5081.61 | N73: Online | O73: Cash
A74: ORD10073 | B74: 45751 | C74: East | D74: Jharkhand | E74: Amit | F74: Electronics | G74: Laptop | H74: 1 | I74: 61013.64 | J74: 0.05 | K74: 57962.96 | L74: 44368.59 | M74: 13594.37 | N74: Retail | O74: Cash
A75: ORD10074 | B75: 45977 | C75: West | D75: Goa | E75: Priya | F75: Electronics | G75: Tablet | H75: 1 | I75: 20961.61 | J75: 0.05 | K75: 19913.53 | L75: 16774.12 | M75: 3139.41 | N75: Corporate | O75: Cash
A76: ORD10075 | B76: 45719 | C76: North | D76: Delhi | E76: Vikram | F76: Electronics | G76: Tablet | H76: 5 | I76: 20896.15 | J76: 0.03 | K76: 101346.31 | L76: 78249.69 | M76: 23096.62 | N76: Retail | O76: Cash
A77: ORD10076 | B77: 45810 | C77: East | D77: Odisha | E77: Kavya | F77: Home Appliances | G77: Microwave | H77: 5 | I77: 11618.65 | J77: 0.08 | K77: 53445.77 | L77: 39584.76 | M77: 13861.01 | N77: Retail | O77: Credit Card
A78: ORD10077 | B78: 45672 | C78: South | D78: Andhra Pradesh | E78: Kavya | F78: Office Supplies | G78: Desk | H78: 6 | I78: 14985.22 | J78: 0.08 | K78: 82718.44 | L78: 57934.12 | M78: 24784.32 | N78: Online | O78: UPI
A79: ORD10078 | B79: 45853 | C79: South | D79: Tamil Nadu | E79: Rahul | F79: Office Supplies | G79: Printer | H79: 1 | I79: 15496.75 | J79: 0.08 | K79: 14257.01 | L79: 9329.08 | M79: 4927.93 | N79: Corporate | O79: Credit Card
A80: ORD10079 | B80: 45672 | C80: South | D80: Karnataka | E80: Amit | F80: Electronics | G80: Headphones | H80: 7 | I80: 4412.75 | J80: 0.05 | K80: 29344.8 | L80: 22447.3 | M80: 6897.5 | N80: Online | O80: Cash
A81: ORD10080 | B81: 45940 | C81: South | D81: Andhra Pradesh | E81: Sneha | F81: Office Supplies | G81: Desk | H81: 7 | I81: 14220.51 | J81: 0.05 | K81: 94566.4 | L81: 74885.52 | M81: 19680.88 | N81: Retail | O81: Debit Card
A82: ORD10081 | B82: 45867 | C82: West | D82: Goa | E82: Neha | F82: Electronics | G82: Smartphone | H82: 6 | I82: 30551.76 | J82: 0.1 | K82: 164979.51 | L82: 107795.61 | M82: 57183.9 | N82: Corporate | O82: Net Banking
A83: ORD10082 | B83: 45944 | C83: East | D83: Jharkhand | E83: Sneha | F83: Furniture | G83: Coffee Table | H83: 8 | I83: 7851.31 | J83: 0.08 | K83: 57785.65 | L83: 46523.18 | M83: 11262.47 | N83: Corporate | O83: Debit Card
... A101: ORD10100 | B101: 45811 | C101: North | D101: Uttar Pradesh | E101: Rahul | F101: Home Appliances | G101: Microwave | H101: 1 | I101: 11993.02 | J101: 0.08 | K101: 11033.58 | L101: 7725.92 | M101: 3307.66 | N101: Corporate | O101: UPI
A102: ORD10101 | B102: 45886 | C102: North | D102: Delhi | E102: Amit | F102: Home Appliances | G102: Microwave | H102: 8 | I102: 11874.87 | K102: 92148.98 | L102: 75247.43 | M102: 16901.55 | N102: Retail | O102: Debit Card
A103: ORD10102 | B103: 45968 | C103: North | D103: Punjab | E103: Sneha | F103: Home Appliances | G103: Air Conditioner | H103: 3 | I103: 51204.97 | J103: 0 | K103: 153614.9 | L103: 130274.19 | M103: 23340.71 | N103: Corporate | O103: Net Banking
A104: ORD10103 | B104: 45682 | C104: South | D104: Andhra Pradesh | E104: Rahul | F104: Office Supplies | G104: Stationery Kit | H104: 1 | I104: 717.78 | J104: 0.08 | K104: 660.36 | L104: 544.01 | M104: 116.35 | N104: Online | O104: Net Banking
A105: ORD10104 | B105: 45907 | C105: North | D105: Punjab | E105: Amit | F105: Furniture | G105: Dining Table | H105: 8 | I105: 29905.11 | J105: 0.03 | K105: 232063.67 | L105: 175511.34 | M105: 56552.33 | N105: Retail | O105: Cash
A106: ORD10105 | B106: 45760 | C106: East | D106: Bihar | E106: Kavya | F106: Electronics | G106: Tablet | H106: 7 | I106: 23039.6 | J106: 0.08 | K106: 148375.05 | L106: 93946.9 | M106: 54428.15 | N106: Retail | O106: Debit Card
A107: ORD10106 | B107: 45661 | C107: East | D107: West Bengal | E107: Priya | F107: Furniture | G107: Bookshelf | H107: 8 | I107: 10896.22 | J107: 0.05 | K107: 82811.25 | L107: 62719.8 | M107: 20091.45 | N107: Online | O107: UPI
A108: ORD10107 | B108: 45908 | C108: East | D108: West Bengal | E108: Kavya | F108: Home Appliances | G108: Air Conditioner | H108: 6 | I108: 47366.45 | J108: 0.05 | K108: 269988.75 | L108: 231564.47 | M108: 38424.28 | N108: Online | O108: Cash
A109: ORD10108 | B109: 45842 | C109: South | D109: Andhra Pradesh | E109: Rahul | F109: Electronics | G109: Monitor | H109: 5 | I109: 18769.5 | J109: 0.05 | K109: 89155.14 | L109: 65544.2 | M109: 23610.94 | N109: Corporate | O109: Net Banking
A110: ORD10109 | B110: 45815 | C110: West | D110: Gujarat | E110: Neha | F110: Home Appliances | G110: Air Conditioner | H110: 5 | I110: 49783.85 | J110: 0 | K110: 248919.24 | L110: 182247.36 | M110: 66671.88 | N110: Online | O110: Credit Card
A111: ORD10110 | B111: 45950 | C111: North | D111: Delhi | E111: Kavya | F111: Electronics | G111: Laptop | H111: 7 | I111: 63797 | J111: 0.08 | K111: 410852.66 | L111: 276249.49 | M111: 134603.17 | N111: Online | O111: Debit Card
A112: ORD10111 | B112: 45716 | C112: East | D112: Bihar | E112: Kavya | F112: Furniture | G112: Bookshelf | H112: 6 | I112: 11199.6 | J112: 0.03 | K112: 65181.7 | L112: 55918.11 | M112: 9263.59 | N112: Retail | O112: Cash
A113: ORD10112 | B113: 45916 | C113: East | D113: West Bengal | E113: Rahul | F113: Home Appliances | G113: Washing Machine | H113: 3 | I113: 34136.8 | J113: 0.03 | K113: 99338.09 | L113: 66034.52 | M113: 33303.57 | N113: Online | O113: Cash
A114: ORD10113 | B114: 45835 | C114: North | D114: Haryana | E114: Arjun | F114: furniture | G114: Bookshelf | H114: 4 | I114: 11871.04 | J114: 0.03 | K114: 46059.63 | L114: 32937.15 | M114: 13122.48 | N114: Corporate | O114: UPI
A115: ORD10001 | B115: 45745 | C115: South | D115: Telangana | E115: Arjun | F115: Office Supplies | G115: Stationery Kit | H115: 5 | I115: 661.47 | J115: 0.03 | K115: 3208.15 | L115: 2033.77 | M115: 1174.38 | N115: Retail | O115: Debit Card
A116: ORD10115 | B116: 45883 | C116: North | D116: Delhi | E116: Amit | F116: Electronics | G116: Smartphone | H116: 4 | I116: 27770.03 | J116: 0.03 | K116: 107747.71 | L116: 90893.97 | M116: 16853.74 | N116: Retail | O116: Debit Card
A117: ORD10116 | B117: 45697 | C117: East | D117: Odisha | E117: Priya | F117: Electronics | G117: Monitor | H117: 8 | I117: 18527.79 | J117: 0 | K117: 148222.28 | L117: 122178.09 | M117: 26044.19 | N117: Online | O117: Cash
A118: ORD10117 | B118: 45825 | C118: West | D118: Rajasthan | E118: Kavya | F118: Office Supplies | G118: Desk | H118: 5 | I118: 13478.14 | J118: 0.1 | K118: 60651.64 | L118: 49211.66 | M118: 11439.98 | N118: Retail | O118: Debit Card
A119: ORD10118 | B119: 45664 | C119: West | D119: Maharashtra | E119: Vikram | F119: Furniture | G119: Sofa | H119: 5 | I119: 32922.32 | J119: 0.08 | K119: 151442.68 | L119: 121252.88 | M119: 30189.8 | N119: Online | O119: Cash
A120: ORD10119 | B120: 46013 | C120: West | D120: Rajasthan | E120: Arjun | F120: Furniture | G120: Dining Table | H120: 8 | I120: 27261.33 | J120: 0.08 | K120: 200643.41 | L120: 132140.21 | M120: 68503.2 | N120: Corporate | O120: Cash
A121: ORD10120 | B121: 46001 | C121: South | D121: Tamil Nadu | E121: Priya | F121: Electronics | G121: Tablet | H121: 1 | I121: 22210.65 | J121: 0 | K121: 22210.65 | L121: 15778.6 | M121: 6432.05 | N121: Online | O121: Debit Card
A122: ORD10121 | B122: 46009 | C122: East | D122: Odisha | E122: Amit | F122: Furniture | G122: Bed | H122: 4 | I122: 28461.59 | J122: 0.08 | K122: 104738.64 | L122: 84766.41 | M122: 19972.23 | N122: Online | O122: Net Banking
A123: ORD10122 | B123: 45963 | C123: South | D123: Telangana | E123: Sneha | F123: Electronics | G123: Smartphone | H123: 6 | I123: 29260.24 | J123: 0.08 | K123: 161516.52 | L123: 101913.38 | M123: 59603.14 | N123: Online | O123: Cash
A124: ORD10123 | B124: 45715 | C124: South | D124: Tamil Nadu | E124: Rahul | F124: Home Appliances | G124: Air Conditioner | H124: 7 | I124: 44664.01 | J124: 0.1 | K124: 281383.26 | L124: 199568.28 | M124: 81814.98 | N124: Retail | O124: Credit Card
A125: ORD10124 | B125: 45945 | C125: North | D125: Delhi | E125: Sneha | F125: Home Appliances | G125: Mixer Grinder | H125: 1 | I125: 4730.9 | J125: 0.1 | K125: 4257.81 | L125: 3348.7 | M125: 909.11 | N125: Retail | O125: Net Banking
... A131: ORD10130 | B131: 45871 | C131: South | D131: Tamil Nadu | E131: Neha | F131: Electronics | G131: Headphones | H131: 1 | I131: 4759.29 | J131: 0.08 | K131: 4378.55 | L131: 2756.33 | M131: 1622.22 | N131: Online | O131: UPI
A132: ORD10131 | B132: 46010 | C132: North | D132: Delhi | E132: Neha | F132: Electronics | G132: Monitor | H132: 4 | I132: 17556.53 | J132: 0.08 | K132: 64608.02 | L132: 54651.73 | M132: 9956.29 | N132: Corporate | O132: UPI
A133: ORD10132 | B133: 45779 | C133: West | D133: Gujarat | E133: Amit | F133: Furniture | G133: Dining Table | H133: 6 | I133: 27202.98 | J133: 0.15 | K133: 138735.22 | L133: 92703.73 | M133: 46031.49 | N133: Online | O133: Credit Card
A134: ORD10133 | B134: 45880 | C134: North | D134: Uttar Pradesh | E134: Amit | F134: Furniture | G134: Coffee Table | H134: 3 | I134: 9038.86 | J134: 0.08 | K134: 24947.26 | L134: 19159.12 | M134: 5788.14 | N134: Corporate | O134: Credit Card
A135: ORD10134 | B135: 45865 | C135: West | D135: Goa | E135: Priya | F135: Office Supplies | G135: Notebook | H135: 6 | I135: 254.49 | J135: 0.05 | K135: 1450.59 | L135: 1129.42 | M135: 321.17 | N135: Corporate | O135: Credit Card
A136: ORD10135 | B136: 45669 | C136: West | D136: Rajasthan | E136: Rahul | F136: Electronics | G136: Monitor | H136: 2 | I136: 17823.19 | J136: 0.08 | K136: 32794.67 | L136: 25002.23 | M136: 7792.44 | N136: Retail | O136: Cash
A137: ORD10136 | B137: 45957 | C137: East | D137: Bihar | E137: Arjun | F137: Home Appliances | G137: Mixer Grinder | H137: 8 | I137: 5297.47 | J137: 0.05 | K137: 40260.74 | L137: 25383.54 | M137: 14877.2 | N137: Corporate | O137: Credit Card
A138: ORD10137 | B138: 45864 | C138: East | D138: West Bengal | E138: Kavya | F138: Home Appliances | G138: Microwave | H138: 3 | I138: 11196.53 | J138: 0.05 | K138: 31910.11 | L138: 21473.42 | M138: 10436.69 | N138: Retail | O138: Net Banking
A139: ORD10138 | B139: 45809 | C139: North | D139: Delhi | E139: Arjun | F139: Home Appliances | G139: Air Conditioner | H139: 5 | I139: 46816.78 | J139: 0.05 | K139: 222379.71 | L139: 190587.39 | M139: 31792.32 | N139: Corporate | O139: Debit Card
A140: ORD10139 | B140: 45900 | C140: East | D140: Jharkhand | E140: Priya | F140: Office Supplies | G140: Notebook | H140: 2 | I140: 253.91 | J140: 0.1 | K140: 457.04 | L140: 355.21 | M140: 101.83 | N140: Corporate | O140: Cash
A141: ORD10140 | B141: 45955 | C141: North | D141: Delhi | E141: Priya | F141: Office Supplies | G141: Printer | H141: 3 | I141: 15662.4 | J141: 0.05 | K141: 44637.84 | L141: 34123.19 | M141: 10514.65 | N141: Retail | O141: Credit Card
A142: ORD10141 | B142: 45787 | C142: North | D142: Delhi | E142: Neha | F142: Home Appliances | G142: Air Conditioner | H142: 5 | I142: 47579.94 | J142: 0.05 | K142: 226004.74 | L142: 159608.17 | M142: 66396.57 | N142: Retail | O142: UPI
...

Sheet Cleaned_Sales_Data
A1: Order_ID | B1: Order_Date | C1: Region | D1: State | E1: Salesperson | F1: Category | G1: Product | H1: Quantity | I1: Unit_Price | J1: Discount | K1: Revenue | L1: Cost | M1: Profit | N1: Customer_Type | O1: Payment_Mode
A2: ORD10785 | B2: 45748 | C2: East | D2: Bihar | E2: Vikram | F2: Office Supplies | G2: Notebook | H2: 1 | I2: 241.09 | J2: 0.15 | K2: 204.93 | L2: 163.98 | M2: 40.95 | N2: Corporate | O2: Net Banking
A3: ORD10711 | B3: 46000 | C3: South | D3: Andhra Pradesh | E3: Amit | F3: Office Supplies | G3: Notebook | H3: 1 | I3: 267.39 | J3: 0.1 | K3: 240.65 | L3: 197.86 | M3: 42.79 | N3: Online | O3: Cash
A4: ORD10089 | B4: 45923 | C4: South | D4: Karnataka | E4: Neha | F4: Office Supplies | G4: Notebook | H4: 1 | I4: 243.37 | J4: 0 | K4: 243.37 | L4: 194.89 | M4: 48.48 | N4: Retail | O4: Credit Card
A5: ORD10577 | B5: 45983 | C5: West | D5: Maharashtra | E5: Arjun | F5: Office Supplies | G5: Notebook | H5: 1 | I5: 234.23 | J5: 0.1 | K5: 210.8 | L5: 159.98 | M5: 50.82 | N5: Online | O5: Credit Card
A6: ORD10806 | B6: 45872 | C6: South | D6: Tamil Nadu | E6: Arjun | F6: Office Supplies | G6: Notebook | H6: 1 | I6: 269.68 | J6: 0 | K6: 269.68 | L6: 218.73 | M6: 50.95 | N6: Retail | O6: Debit Card
A7: ORD11005 | B7: 45842 | C7: South | D7: Karnataka | E7: Vikram | F7: Office Supplies | G7: Notebook | H7: 1 | I7: 262.61 | J7: 0 | K7: 262.61 | L7: 202.08 | M7: 60.53 | N7: Corporate | O7: UPI
A8: ORD10289 | B8: 45813 | C8: North | D8: Uttar Pradesh | E8: Priya | F8: Office Supplies | G8: Notebook | H8: 1 | I8: 263.42 | J8: 0.1 | K8: 237.07 | L8: 168.43 | M8: 68.64 | N8: Retail | O8: Debit Card
A9: ORD10371 | B9: 45985 | C9: West | D9: Goa | E9: Sneha | F9: Office Supplies | G9: Notebook | H9: 1 | I9: 252.17 | J9: 0.03 | K9: 244.61 | L9: 168.91 | M9: 75.7 | N9: Online | O9: Cash
A10: ORD10164 | B10: 45693 | C10: North | D10: Uttar Pradesh | E10: Sneha | F10: Office Supplies | G10: Notebook | H10: 2 | I10: 243.49 | J10: 0.1 | K10: 438.28 | L10: 353 | M10: 85.28 | N10: Retail | O10: UPI
A11: ORD10407 | B11: 45865 | C11: South | D11: Karnataka | E11: Rahul | F11: Office Supplies | G11: Stationery Kit | H11: 1 | I11: 669.32 | J11: 0.1 | K11: 602.39 | L11: 507.99 | M11: 94.4 | N11: Retail | O11: Cash
A12: ORD10139 | B12: 45900 | C12: East | D12: Jharkhand | E12: Priya | F12: Office Supplies | G12: Notebook | H12: 2 | I12: 253.91 | J12: 0.1 | K12: 457.04 | L12: 355.21 | M12: 101.83 | N12: Corporate | O12: Cash
A13: ORD10571 | B13: 45914 | C13: South | D13: Telangana | E13: Vikram | F13: Office Supplies | G13: Notebook | H13: 2 | I13: 242.63 | J13: 0 | K13: 485.25 | L13: 377.2 | M13: 108.05 | N13: Retail | O13: Debit Card
... A1181: ORD10056 | B1181: 45811 | C1181: West | D1181: Maharashtra | E1181: Sneha | F1181: Electronics | G1181: Laptop | H1181: 8 | I1181: 66228.53 | J1181: 0.05 | K1181: 503336.86 | L1181: 325786.71 | M1181: 177550.15 | N1181: Corporate | O1181: Debit Card

Sheet Monthly Trend
A3: Row Labels | B3: Total Revenue | C3: Total Profit
A4: Jan | B4: 9421909.4 | C4: 2403536
A5: Feb | B5: 8311136 | C5: 2127785.9
A6: Mar | B6: 9710176.6 | C6: 2473852.6
A7: Apr | B7: 9549827.9 | C7: 2401717.6
A8: May | B8: 9934935 | C8: 2598244.6
A9: Jun | B9: 9283745.9 | C9: 2412663.7
A10: Jul | B10: 8869023.6 | C10: 2187474.4
A11: Aug | B11: 8970946.1 | C11: 2253862.8
A12: Sep | B12: 8954553 | C12: 2381184.3
A13: Oct | B13: 9992152.9 | C13: 2686815.4
A14: Nov | B14: 12873167 | C14: 3335606.8
A15: Dec | B15: 8891700.4 | C15: 2277265.6
A16: Grand Total | B16: 1.1476327e+08 | C16: 29540010

Sheet Region Analysis
A3: Row Labels | B3: Total Revenue | C3: Total Profit
A4: East | B4: 22862092 | C4: 5940513.2
A5: North | B5: 31802415 | C5: 8068792
A6: South | B6: 32131258 | C6: 8199036.3
A7: Unknown | B7: 659386.42 | C7: 188943.9
A8: West | B8: 27308122 | C8: 7142724.2
A9: Grand Total | B9: 1.1476327e+08 | C9: 29540010

Sheet Category Analysis
A3: Row Labels | B3: Total Revenue | C3: Total Profit
A4: Electronics | B4: 49794962 | C4: 12880500
A5: Furniture | B5: 17817791 | C5: 4649348.2
A6: Home Appliances | B6: 39199478 | C6: 9928626.7
A7: Office Supplies | B7: 7951041.2 | C7: 2081534.9
A8: Grand Total | B8: 1.1476327e+08 | C8: 29540010

Sheet Product Analysis
A3: Row Labels | B3: Total Revenue | C3: Total Profit
A4: Laptop | B4: 21947898 | C4: 5735129.8
A5: Air Conditioner | B5: 15323679 | C5: 3706946.9
A6: Washing Machine | B6: 10078775 | C6: 2541211.8
A7: Refrigerator | B7: 9941796.8 | C7: 2662958.6
A8: Tablet | B8: 9818729 | C8: 2511674.6
A9: Smartphone | B9: 9761957.8 | C9: 2571841.2
A10: Monitor | B10: 6934566.5 | C10: 1725547.2
A11: Sofa | B11: 5682407.1 | C11: 1565870.9
A12: Bed | B12: 4412698.8 | C12: 1032446.3
A13: Dining Table | B13: 4199874.3 | C13: 1166260.8
A14: Printer | B14: 3261707.2 | C14: 840484.97
A15: Desk | B15: 2916989.1 | C15: 791062.77
... A24: Grand Total | B24: 1.1476327e+08 | C24: 29540010

Sheet Salesperson Analysis
A3: Row Labels | B3: Total Revenue | C3: Total Profit
A4: Arjun | B4: 15884616 | C4: 3933996.5
A5: Kavya | B5: 15229045 | C5: 3965627.8
A6: Sneha | B6: 15171648 | C6: 4024259.1
A7: Amit | B7: 14653316 | C7: 3668662.8
A8: Rahul | B8: 14531746 | C8: 3739093.5
A9: Vikram | B9: 13597235 | C9: 3402812.8
A10: Neha | B10: 12956291 | C10: 3520397.1
A11: Priya | B11: 11734342 | C11: 2986407.1
A12: Unknown | B12: 1005034.5 | C12: 298752.99
A13: Grand Total | B13: 1.1476327e+08 | C13: 29540010

Sheet Discount Analysis
A3: Discount % | B3: Total Revenue | C3: Total Profit
A4: 0 | B4: 19418494 | C4: 4699612.9
A5: 0.03 | B5: 20083786 | C5: 5377251.1
A6: 0.05 | B6: 31962182 | C6: 8283033.1
A7: 0.08 | B7: 19560063 | C7: 5248118.5
A8: 0.1 | B8: 18841565 | C8: 4736774.5
A9: 0.15 | B9: 4897182.8 | C9: 1195219.5
A10: Grand Total | B10: 1.1476327e+08 | C10: 29540010

Sheet Analysis_Sheet
A1: KPI | B1: Value | D1: Region Performance Summary | K1: Selected Region | L1: East
A2: Total Revenue | B2: =SUM(Cleaned_Sales_Data[Revenue]) -> 1.1476327e+08 | D2: Region | E2: Total Revenue | F2: Total Profit | G2: Order Count | H2: Profit Margin | I2: Performance Status | K2: Total Revenue | L2: =_xlfn.XLOOKUP($L$1,$D$3:$D$7,$E$3:$E$7,"Not Found") -> 22862092
A3: Total Profit | B3: =SUM(Cleaned_Sales_Data[Profit]) -> 29540010 | D3: South | E3: =SUMIFS(Cleaned_Sales_Data[Revenue],Cleaned_Sales_Data[Region],Table1[[#This Row],[Region]]) -> 32131258 | F3: =SUMIFS(Cleaned_Sales_Data[Profit],Cleaned_Sales_Data[Region],Table1[[#This Row],[Region]]) -> 8199036.3 | G3: =COUNTIFS(Cleaned_Sales_Data[Region],D3) -> 331 | H3: =Table1[[#This Row],[Total Profit]]/Table1[[#This Row],[Total Revenue]] -> 0.25517321 | I3: =IF(H3>=25%,"Healthy","Needs Review") -> Healthy | K3: Total Profit | L3: =_xlfn.XLOOKUP(L1,$D$3:$D$7,$F$3:$F$7,"Not Found") -> 5940513.2
A4: Total Orders | B4: =COUNTA(Cleaned_Sales_Data[Order_ID]) -> 1180 | D4: North | E4: =SUMIFS(Cleaned_Sales_Data[Revenue],Cleaned_Sales_Data[Region],Table1[[#This Row],[Region]]) -> 31802415 | F4: =SUMIFS(Cleaned_Sales_Data[Profit],Cleaned_Sales_Data[Region],Table1[[#This Row],[Region]]) -> 8068792 | G4: =COUNTIFS(Cleaned_Sales_Data[Region],D4) -> 325 | H4: =Table1[[#This Row],[Total Profit]]/Table1[[#This Row],[Total Revenue]] -> 0.25371633 | I4: =IF(H4>=25%,"Healthy","Needs Review") -> Healthy | K4: Order Count | L4: =_xlfn.XLOOKUP(L1,$D$3:$D$7,$G$3:$G$7,"Not Found") -> 260
A5: Total Quantity | B5: =SUM(Cleaned_Sales_Data[Quantity]) -> 5218 | D5: East | E5: =SUMIFS(Cleaned_Sales_Data[Revenue],Cleaned_Sales_Data[Region],Table1[[#This Row],[Region]]) -> 22862092 | F5: =SUMIFS(Cleaned_Sales_Data[Profit],Cleaned_Sales_Data[Region],Table1[[#This Row],[Region]]) -> 5940513.2 | G5: =COUNTIFS(Cleaned_Sales_Data[Region],D5) -> 260 | H5: =Table1[[#This Row],[Total Profit]]/Table1[[#This Row],[Total Revenue]] -> 0.25984119 | I5: =IF(H5>=25%,"Healthy","Needs Review") -> Healthy | K5: Profit Margin | L5: =_xlfn.XLOOKUP(L1,$D$3:$D$7,$H$3:$H$7,"Not Found") -> 0.25984119
A6: Average Order Value | B6: =SUM(Cleaned_Sales_Data[Revenue])/COUNTA(Cleaned_Sales_Data[Order_ID]) -> 97257.011 | D6: West | E6: =SUMIFS(Cleaned_Sales_Data[Revenue],Cleaned_Sales_Data[Region],Table1[[#This Row],[Region]]) -> 27308122 | F6: =SUMIFS(Cleaned_Sales_Data[Profit],Cleaned_Sales_Data[Region],Table1[[#This Row],[Region]]) -> 7142724.2 | G6: =COUNTIFS(Cleaned_Sales_Data[Region],D6) -> 256 | H6: =Table1[[#This Row],[Total Profit]]/Table1[[#This Row],[Total Revenue]] -> 0.26156044 | I6: =IF(H6>=25%,"Healthy","Needs Review") -> Healthy
A7: Profit Margin | B7: =SUM(Cleaned_Sales_Data[Profit])/SUM(Cleaned_Sales_Data[Revenue]) -> 0.2573995 | D7: Unknown | E7: =SUMIFS(Cleaned_Sales_Data[Revenue],Cleaned_Sales_Data[Region],Table1[[#This Row],[Region]]) -> 659386.42 | F7: =SUMIFS(Cleaned_Sales_Data[Profit],Cleaned_Sales_Data[Region],Table1[[#This Row],[Region]]) -> 188943.9 | G7: =COUNTIFS(Cleaned_Sales_Data[Region],D7) -> 8 | H7: =Table1[[#This Row],[Total Profit]]/Table1[[#This Row],[Total Revenue]] -> 0.28654503 | I7: =IF(H7>=25%,"Healthy","Needs Review") -> Healthy
K8: Selected Salesperson | L8: Amit
K9: Total Revenue | L9: =INDEX('Salesperson Analysis'!$B:$B,MATCH(L8,'Salesperson Analysis'!$A:$A,0)) -> 14653316
A10: KPI PivotTable | K10: Total Profit | L10: =INDEX('Salesperson Analysis'!$C:$C,MATCH(L8,'Salesperson Analysis'!$A:$A,0)) -> 3668662.8
A11: Total Revenue | B11: 1.1476327e+08
A12: Total Profit | B12: 29540010
A13: Total Orders | B13: 1180
A14: Total Quantity | B14: 5218
A15: Average Order Value
A16: Profit Margin

Sheet Dashboard
A1: Sales Performance & MIS Dashboard
A3: Total Revenue | G3: Total Profit | M3: Total Orders | S3: Total Quantity | Y3: Average Order Value | AE3: Profit Margin
A4: =GETPIVOTDATA("Total Revenue",Analysis_Sheet!$A$10) -> 1.1476327e+08 | G4: =GETPIVOTDATA("Total Profit",Analysis_Sheet!$A$10) -> 29540010 | M4: =GETPIVOTDATA("Total Orders",Analysis_Sheet!$A$10) -> 1180 | S4: =GETPIVOTDATA("Total Quantity",Analysis_Sheet!$A$10) -> 5218 | Y4: =A4/M4 -> 97257.011 | AE4: =G4/A4 -> 0.2573995
